.gitignore
.installed.cfg
.mr.developer.cfg
CHANGES.rst
CONTRIBUTORS.rst
MANIFEST.in
README.rst
TODO.txt
bootstrap.py
buildout.cfg.in
picked.cfg
setup.cfg
setup.py
versions-4.3.x.cfg
conf/test-3.3.x.cfg
conf/test-4.1.x.cfg
mr/__init__.py
mr/__init__.pyc
mr.migrator.egg-info/PKG-INFO
mr.migrator.egg-info/SOURCES.txt
mr.migrator.egg-info/dependency_links.txt
mr.migrator.egg-info/entry_points.txt
mr.migrator.egg-info/namespace_packages.txt
mr.migrator.egg-info/not-zip-safe
mr.migrator.egg-info/requires.txt
mr.migrator.egg-info/top_level.txt
mr/migrator/__init__.py
mr/migrator/__init__.pyc
mr/migrator/configure.zcml
mr/migrator/browser/__init__.py
mr/migrator/browser/__init__.pyc
mr/migrator/browser/configure.zcml
mr/migrator/browser/helper.py
mr/migrator/browser/helper.pyc
mr/migrator/browser/interfaces.py
mr/migrator/locales/manual.pot
mr/migrator/locales/mr.migrator.pot
mr/migrator/locales/plone.pot
mr/migrator/locales/es/LC_MESSAGES/mr.migrator.po
mr/migrator/locales/es/LC_MESSAGES/plone.po
mr/migrator/profiles/default/actions.xml
mr/migrator/profiles/default/metadata.xml
mr/migrator/profiles/uninstall/actions.xml
mr/migrator/profiles/uninstall/browserlayer.xml
mr/migrator/recipe/README.txt
mr/migrator/recipe/__init__.py
mr/migrator/recipe/__init__.pyc
mr/migrator/recipe/tests/__init__.py
mr/migrator/recipe/tests/test_docs.py
mr/migrator/runner/__init__.py
mr/migrator/runner/__init__.pyc