Metadata-Version: 1.1
Name: mr.migrator
Version: 1.2
Summary: Drive-by transmogrifiction made easy!
Home-page: https://github.com/collective/mr.migrator
Author: Alex Clark
Author-email: aclark@aclark.net
License: GPL
Keywords: buildout crawler spider plone transmogrifierless
Platform: UNKNOWN
Classifier: Framework :: Buildout
Classifier: Intended Audience :: Developers
Classifier: Topic :: Software Development :: Build Tools
Classifier: License :: OSI Approved :: Zope Public License
